{
  "id": "sans-internet-storm-center-infocon-green-isc-sans-edu-2025-11-23-31a0a85a",
  "source_id": "sans-internet-storm-center-infocon-green-isc-sans-edu",
  "guid": "https://isc.sans.edu/diary/rss/32512",
  "title": "Wireshark 4.4.1 Released, (Sun, Nov 23rd)",
  "url": "https://isc.sans.edu/diary/rss/32512",
  "published_at": "2025-11-23T10:38:53+00:00",
  "fetched_at": "2025-11-23T11:17:34.491618+00:00Z",
  "status": "fetched",
  "content": {
    "raw": "Wireshark release 4.6.1 fixes 2 vulnerabilities and 20 bugs.",
    "full": "",
    "processed": ""
  },
  "analysis": {
    "score": null,
    "relevance_score": null,
    "threat_category": null,
    "summary": null,
    "key_entities": [],
    "ttps": []
  },
  "content_source": "rss",
  "content_fetch_method": null,
  "processing_metadata": {}
}