{
  "id": "infosecurity-magazine-2025-11-17-ff31b431",
  "source_id": "infosecurity-magazine",
  "guid": "https://www.infosecurity-magazine.com/news/jlr-posts-639m-q2-losses/",
  "title": "Cyber-Attack Costs Carmaker JLR $258m in Q2",
  "url": "https://www.infosecurity-magazine.com/news/jlr-posts-639m-q2-losses/",
  "published_at": "2025-11-17T09:30:00+00:00",
  "fetched_at": "2025-11-17T11:18:38.305887+00:00Z",
  "status": "fetched",
  "content": {
    "raw": "Carmaker JLR has posted $639m Q2 losses and a one-off $258m hit after a major ransomware attack",
    "full": "",
    "processed": ""
  },
  "analysis": {
    "score": null,
    "relevance_score": null,
    "threat_category": null,
    "summary": null,
    "key_entities": [],
    "ttps": []
  },
  "content_source": "rss",
  "content_fetch_method": null,
  "processing_metadata": {}
}