{
  "id": "bleeping-computer-2025-11-19-16fc0b00",
  "source_id": "bleeping-computer",
  "guid": "https://www.bleepingcomputer.com/news/security/new-wrthug-campaign-hijacks-thousands-of-end-of-life-asus-routers/",
  "title": "New WrtHug campaign hijacks thousands of end-of-life ASUS routers",
  "url": "https://www.bleepingcomputer.com/news/security/new-wrthug-campaign-hijacks-thousands-of-end-of-life-asus-routers/",
  "published_at": "2025-11-19T14:35:15+00:00",
  "fetched_at": "2025-11-20T11:17:44.573005+00:00Z",
  "status": "fetched",
  "content": {
    "raw": "Thousands of ASUS WRT routers, mostly end-of-life or outdated devices, have been hijacked in a global campaign called Operation WrtHug that exploits six vulnerabilities. [...]",
    "full": "",
    "processed": ""
  },
  "analysis": {
    "score": null,
    "relevance_score": null,
    "threat_category": null,
    "summary": null,
    "key_entities": [],
    "ttps": []
  },
  "content_source": "rss",
  "content_fetch_method": null,
  "processing_metadata": {}
}